trajcalc/__init__.py
trajcalc/__main__.py
trajcalc/logger/__init__.py
trajcalc/tests/__init__.py
MLB_TrajectoryCalculator-0.0.3.dist-info/LICENSE
MLB_TrajectoryCalculator-0.0.3.dist-info/METADATA
MLB_TrajectoryCalculator-0.0.3.dist-info/WHEEL
MLB_TrajectoryCalculator-0.0.3.dist-info/top_level.txt
MLB_TrajectoryCalculator-0.0.3.dist-info/RECORD
