Metadata-Version: 2.1
Name: MLB-TrajectoryCalculator
Version: 0.0.3
Summary: A package containing utilities for calculating MLB ball trajectories
Home-page: https://github.com/JLpython-py/MLB-TrajectoryCalculator
Author: Jacob Lee
Author-email: JLpython@outlook.com
License: UNKNOWN
Platform: UNKNOWN
Classifier: Development Status :: 1 - Planning
Classifier: License :: OSI Approved :: MIT License
Classifier: Operating System :: OS Independent
Classifier: Programming Language :: Python :: 3
Classifier: Programming Language :: Python :: 3.6
Classifier: Programming Language :: Python :: 3.7
Classifier: Programming Language :: Python :: 3.8
Classifier: Programming Language :: Python :: 3.9
Classifier: Programming Language :: Python :: 3.10
Requires-Python: >=3.6
License-File: LICENSE
